LICENSE
MANIFEST.in
README.md
setup.py
gkligo/__init__.py
gkligo/__version__.py
gkligo.egg-info/PKG-INFO
gkligo.egg-info/SOURCES.txt
gkligo.egg-info/dependency_links.txt
gkligo.egg-info/entry_points.txt
gkligo.egg-info/requires.txt
gkligo.egg-info/top_level.txt
gkligo/scripts/__init__.py
gkligo/scripts/python/=
gkligo/scripts/python/__init__.py
gkligo/scripts/python/config_download_example.yaml
gkligo/scripts/python/config_reports.yaml
gkligo/scripts/python/config_reports_example.yaml
gkligo/scripts/python/downloadGWAlerts.py
gkligo/scripts/python/generateGWReports.py
gkligo/scripts/python/test.py
gkligo/scripts/python/test.yaml
gkligo/scripts/python/testDaemon.py