Metadata-Version: 2.1
Name: gkligo
Version: 0.2.1
Summary: GW (LIGO) utilities
Home-page: https://github.com/genghisken/gkligo
Author: genghisken
Author-email: ken.w.smith@gmail.com
License: MIT
Classifier: Development Status :: 4 - Beta
Classifier: License :: OSI Approved :: MIT License
Classifier: Programming Language :: Python :: 3.9
Classifier: Topic :: Utilities
Requires-Python: >=3.7
License-File: LICENSE
